stitch/__init__.py
stitch/payins.py
stitch/services/__init__.py
stitch/services/api.py
stitch/utils/__init__.py
stitch/utils/types.py
stitch_money_api-1.3.0.dist-info/METADATA
stitch_money_api-1.3.0.dist-info/WHEEL
stitch_money_api-1.3.0.dist-info/licenses/LICENSE
stitch_money_api-1.3.0.dist-info/RECORD
