Metadata-Version: 2.4
Name: stitch-money-api
Version: 1.3.0
Summary: A package for initiating payments via the Stitch API
Project-URL: Homepage, https://stitch.money/
Project-URL: Documentation, https://docs.stitch.money/
Author-email: Stitch Money <sdks@stitch.money>
License: MIT License
License-File: LICENSE
Classifier: License :: OSI Approved :: MIT License
Classifier: Operating System :: OS Independent
Classifier: Programming Language :: Python :: 3
Requires-Python: >=3.8
Requires-Dist: anyio>=4.4.0
Requires-Dist: backoff>=2.2.1
Requires-Dist: certifi>=2024.7.4
Requires-Dist: cffi>=1.17.0
Requires-Dist: charset-normalizer>=3.3.2
Requires-Dist: cryptography>=43.0.0
Requires-Dist: exceptiongroup>=1.2.2
Requires-Dist: gql>=3.5.0
Requires-Dist: graphql-core>=3.2.3
Requires-Dist: idna>=3.7
Requires-Dist: multidict>=6.0.5
Requires-Dist: pycparser>=2.22
Requires-Dist: requests-toolbelt>=1.0.0
Requires-Dist: requests>=2.32.3
Requires-Dist: sniffio>=1.3.1
Requires-Dist: typing-extensions>=4.12.2
Requires-Dist: urllib3>=2.2.2
Requires-Dist: yarl>=1.9.4
